_bitalign.pypy38-pp73-x86_64-linux-gnu.so
bitalign-0.4.0.dist-info/WHEEL
bitalign-0.4.0.dist-info/top_level.txt
bitalign-0.4.0.dist-info/METADATA
bitalign-0.4.0.dist-info/LICENSE
bitalign-0.4.0.dist-info/RECORD
bitalign/tests.py
bitalign/__init__.py
bitalign/benchmark.py
