Metadata-Version: 2.1
Name: bitalign
Version: 0.4.0
Summary: Shift some bits and see how they line up best.
Home-page: https://github.com/sweeneyde/bitalign
Author: Dennis Sweeney
Author-email: Dennis Sweeney <sweeney.427@osu.edu>
Project-URL: Homepage, https://github.com/sweeneyde/bitalign
Project-URL: Bug Tracker, https://github.com/sweeneyde/bitalign
Classifier: Programming Language :: Python :: 3
Classifier: License :: OSI Approved :: MIT License
Classifier: Operating System :: OS Independent
Requires-Python: >=3.6
License-File: LICENSE
